Workbook

Sheet Model Inputs
B2: Select Scenario: | C2: =IF(B3= "Best Case",1,IF(B3="Base Case",2,IF(B3="Worst Case",3))) -> 3 | F2: Breakage (SBUX)
B3: Worst Case
B4: Default Float Period | C4: 12 | F4: 2020 | G4: =F4+1 -> 2021 | H4: =G4+1 -> 2022 | I4: =H4+1 -> 2023 | J4: =I4+1 -> 2024 | K4: =J4+1 -> 2025
E5: Best Case | F5: 0.19 | G5: 0.19 | H5: 0.19 | I5: 0.19 | J5: 0.19 | K5: 0.19
E6: Base Case | F6: 0.15 | G6: 0.15 | H6: 0.15 | I6: 0.15 | J6: 0.15 | K6: 0.15
E7: Worst Case | F7: 0.1 | G7: 0.1 | H7: 0.1 | I7: 0.1 | J7: 0.1 | K7: 0.1
F9: Breakage (CMG)
F11: 2020 | G11: =F11+1 -> 2021 | H11: =G11+1 -> 2022 | I11: =H11+1 -> 2023 | J11: =I11+1 -> 2024 | K11: =J11+1 -> 2025
E12: Best Case | F12: 0.19 | G12: 0.19 | H12: 0.19 | I12: 0.19 | J12: 0.19 | K12: 0.19
E13: Base Case | F13: 0.15 | G13: 0.15 | H13: 0.15 | I13: 0.15 | J13: 0.15 | K13: 0.15
E14: Worst Case | F14: 0.1 | G14: 0.1 | H14: 0.1 | I14: 0.1 | J14: 0.1 | K14: 0.1
E16: Borrowing Rate | F16: # | G16: Spread | H16: Total Rate
E17: 0.0675
E18: Large Corporation | F18: 1 | G18: 0 | H18: =$E$17+G18 -> 0.0675
E19: Medium-Size Business | F19: 2 | G19: 0.015 | H19: =$E$17+G19 -> 0.0825
E20: Small-Business | F20: 3 | G20: 0.0275 | H20: =$E$17+G20 -> 0.095
E21: Startup | F21: 4 | G21: 0.045 | H21: =$E$17+G21 -> 0.1125

Sheet Revenue Recognition
C2: SBUX (Starbucks)
A3: ='Model Inputs'!C2 -> 3 | C3: Source | D3: Liability ($M)* | E3: YoY Growth (%) | F3: Average Prime Borrow Rate** | G3: Interest Avoided ($M) | H3: % Industry Avg (SBUX) | I3: Est. Reported Breakage ($M)
C4: 10-K FY 2020 | D4: 1457 | E4: =IFERROR(D4/D3-1, " -") -> - | F4: 0.0354 | G4: =D4*$F4 -> 51.5778 | H4: =IF($A$3=1,'Model Inputs'!F$5,IF($A$3=2,'Model Inputs'!F$6,IF($A$3=3,'Model Inputs'!F$7))) -> 0.1 | I4: =D4*H4 -> 145.7
C5: 10-K FY 2021 | D5: 1596 | E5: =IFERROR(D5/D4-1, " -") -> 0.09540151 | F5: 0.0325 | G5: =D5*$F5 -> 51.87 | H5: =IF($A$3=1,'Model Inputs'!F$5,IF($A$3=2,'Model Inputs'!F$6,IF($A$3=3,'Model Inputs'!F$7))) -> 0.1 | I5: =D5*H5 -> 159.6
C6: 10-K FY 2022 | D6: 1642 | E6: =IFERROR(D6/D5-1, " -") -> 0.028822055 | F6: 0.0486 | G6: =D6*$F6 -> 79.8012 | H6: =IF($A$3=1,'Model Inputs'!F$5,IF($A$3=2,'Model Inputs'!F$6,IF($A$3=3,'Model Inputs'!F$7))) -> 0.1 | I6: =D6*H6 -> 164.2
C7: 10-K FY 2023 | D7: 1796 | E7: =IFERROR(D7/D6-1, " -") -> 0.093788063 | F7: 0.082 | G7: =D7*$F7 -> 147.272 | H7: =IF($A$3=1,'Model Inputs'!F$5,IF($A$3=2,'Model Inputs'!F$6,IF($A$3=3,'Model Inputs'!F$7))) -> 0.1 | I7: =D7*H7 -> 179.6
C8: 10-K FY 2024 | D8: 1781 | E8: =IFERROR(D8/D7-1, " -") -> -0.0083518931 | F8: 0.0831 | G8: =D8*$F8 -> 148.0011 | H8: =IF($A$3=1,'Model Inputs'!F$5,IF($A$3=2,'Model Inputs'!F$6,IF($A$3=3,'Model Inputs'!F$7))) -> 0.1 | I8: =D8*H8 -> 178.1
C9: 10-K FY 2025 | D9: 1841 | E9: =IFERROR(D9/D8-1, " -") -> 0.033688939 | F9: 0.0737 | G9: =D9*$F9 -> 135.6817 | H9: =IF($A$3=1,'Model Inputs'!F$5,IF($A$3=2,'Model Inputs'!F$6,IF($A$3=3,'Model Inputs'!F$7))) -> 0.1 | I9: =D9*H9 -> 184.1 | J9: True Total Benefit
C10: Totals: | G10: =SUM(G4:G9) -> 614.2038 | I10: =SUM(I4:I9) -> 1011.3 | J10: =G10+I10 -> 1625.5038
C12: ="Scenario: "&'Model Inputs'!C2 -> Scenario: 3 | E12: Notes: | F12: *Starbucks Gift Card Liability is discoolsed under the line titled "Stored Value Card Liability" on page 72
F13: *Chipotle's Gift Card Liability is discoolsed under the line titled "Gift Card Liability" on page 48 under Revenue Recognition
F14: **Taken the industry average from the Federal Reserves (FRED) own database
F15: ***Not enough info or disclosing to accurately calculate the reported breakage, took industry average based on % of total liability
C17: CNG (Chipotle)
C18: Source | D18: Liability ($M)* | E18: YoY Growth (%) | F18: Average Prime Borrow Rate | G18: Interest Avoided ($M) | H18: % Industry Avg (CMG) | I18: Est. Reported Breakage ($M)
C19: 10-K FY 2020 | D19: 105.4 | E19: =IFERROR(D19/D18-1, " -") -> - | F19: 0.0354 | G19: =D19*$F4 -> 3.73116 | H19: =IF($A$3=1,'Model Inputs'!G$5,IF($A$3=2,'Model Inputs'!G$6,IF($A$3=3,'Model Inputs'!G$7))) -> 0.1 | I19: =D19*H19 -> 10.54
C20: 10-K FY 2021 | D20: 130.8 | E20: =IFERROR(D20/D19-1, " -") -> 0.24098672 | F20: 0.0325 | G20: =D20*$F5 -> 4.251 | H20: =IF($A$3=1,'Model Inputs'!G$5,IF($A$3=2,'Model Inputs'!G$6,IF($A$3=3,'Model Inputs'!G$7))) -> 0.1 | I20: =D20*H20 -> 13.08
C21: 10-K FY 2022 | D21: 145 | E21: =IFERROR(D21/D20-1, " -") -> 0.10856269 | F21: 0.0486 | G21: =D21*$F6 -> 7.047 | H21: =IF($A$3=1,'Model Inputs'!G$5,IF($A$3=2,'Model Inputs'!G$6,IF($A$3=3,'Model Inputs'!G$7))) -> 0.1 | I21: =D21*H21 -> 14.5
C22: 10-K FY 2023 | D22: 164.9 | E22: =IFERROR(D22/D21-1, " -") -> 0.13724138 | F22: 0.082 | G22: =D22*$F7 -> 13.5218 | H22: =IF($A$3=1,'Model Inputs'!G$5,IF($A$3=2,'Model Inputs'!G$6,IF($A$3=3,'Model Inputs'!G$7))) -> 0.1 | I22: =D22*H22 -> 16.49
C23: 10-K FY 2024 | D23: 181.8 | E23: =IFERROR(D23/D22-1, " -") -> 0.10248636 | F23: 0.0831 | G23: =D23*$F8 -> 15.10758 | H23: =IF($A$3=1,'Model Inputs'!G$5,IF($A$3=2,'Model Inputs'!G$6,IF($A$3=3,'Model Inputs'!G$7))) -> 0.1 | I23: =D23*H23 -> 18.18
C24: 10-K FY 2025 | D24: 174.6 | E24: =IFERROR(D24/D23-1, " -") -> -0.03960396 | F24: 0.0737 | G24: =D24*$F9 -> 12.86802 | H24: =IF($A$3=1,'Model Inputs'!G$5,IF($A$3=2,'Model Inputs'!G$6,IF($A$3=3,'Model Inputs'!G$7))) -> 0.1 | I24: =D24*H24 -> 17.46 | J24: True Total Benefit
C25: Totals: | G25: =SUM(G19:G24) -> 56.52656 | I25: =SUM(I19:I24) -> 90.25 | J25: =G25+I25 -> 146.77656

Sheet Business Model
B1: Inputs | F1: Sensitivity Analysis: Annual Benfits by GC Sales Volume (Fixed)
A3: 4 | F3: Business Type | G3: Annual Gift Card Sales: | H3: Breakage Revenue: | I3: Float Value: | J3: Loan Cost Avoided: | K3: Total Annual Benefit: | L3: Est. Redeemed: | N3: Business Type | O3: Total Rate (Fixed)
A4: 4 | B4: Business Type | F4: Very Small Operator (Startup) | G4: =G5/2 -> 6250 | H4: =G4*$C$12 -> 937.5 | I4: =G4*($C$13/12) -> 7812.5 | J4: =G4*($C$13/12)*$O$7 -> 878.90625 | K4: =H4+J4 -> 1816.4062 | L4: =G4*(1-$C$12) -> 5312.5 | N4: Large Corporation | O4: 0.0675
F5: Café/Corner Store (SB) | G5: =G6/2 -> 12500 | H5: =G5*$C$12 -> 1875 | I5: =G5*($C$13/12) -> 15625 | J5: =G5*($C$13/12)*O6 -> 1484.375 | K5: =H5+J5 -> 3359.375 | L5: =G5*(1-$C$12) -> 10625 | N5: Medium-Size Business | O5: 0.0825
A6: 2 | B6: Scenario | F6: Independent Restaurant (SB) | G6: =G7/2 -> 25000 | H6: =G6*$C$12 -> 3750 | I6: =G6*($C$13/12) -> 31250 | J6: =G6*($C$13/12)*O6 -> 2968.75 | K6: =H6+J6 -> 6718.75 | L6: =G6*(1-$C$12) -> 21250 | N6: Small-Business | O6: 0.095
F7: Small Regional Chain (SB) | G7: 50000 | H7: =G7*$C$12 -> 7500 | I7: =G7*($C$13/12) -> 62500 | J7: =G7*($C$13/12)*O6 -> 5937.5 | K7: =H7+J7 -> 13437.5 | L7: =G7*(1-$C$12) -> 42500 | N7: Startup | O7: 0.1125
F8: Mid-Size Retailer (MB) | G8: =G7*1.5 -> 75000 | H8: =G8*$C$12 -> 11250 | I8: =G8*($C$13/12) -> 93750 | J8: =G8*($C$13/12)*O5 -> 7734.375 | K8: =H8+J8 -> 18984.375 | L8: =G8*(1-$C$12) -> 63750
B9: Business Name | C9: Ernst LLC | F9: Larger Operator (LB) | G9: =G8*1.5 -> 112500 | H9: =G9*$C$12 -> 16875 | I9: =G9*($C$13/12) -> 140625 | J9: =G9*($C$13/12)*O4 -> 9492.1875 | K9: =H9+J9 -> 26367.188 | L9: =G9*(1-$C$12) -> 95625
B10: Annual Gift Card Sales ($) | C10: 50000 | F10: Small Franchise Group (LB) | G10: =G9*1.5 -> 168750 | H10: =G10*$C$12 -> 25312.5 | I10: =G10*($C$13/12) -> 210937.5 | J10: =G10*($C$13/12)*O4 -> 14238.281 | K10: =H10+J10 -> 39550.781 | L10: =G10*(1-$C$12) -> 143437.5
B11: Annual Gift Card Redemptions ($) | C11: 40000 | N11: Year | O11: Average Prime Borrow Rate
B12: Breakage Rate (%) | C12: =CHOOSE(A6,'Model Inputs'!F12,'Model Inputs'!F13,'Model Inputs'!F14,) -> 0.15 | N12: 2020 | O12: 0.0354
B13: Float Period (months) | C13: =IF(C11="",'Model Inputs'!C4,(C10/C11)*12) -> 15 | N13: 2021 | O13: 0.0325
B14: Bank Loan Rate (Variable) | C14: =CHOOSE(A4,O21,O22,O23,O24) + CHOOSE(A15,O12,O13,O14,O15,O16,O17) -> 0.0804 | N14: 2022 | O14: 0.0486
A15: =C15-2019 -> 1 | B15: Year | C15: 2020 | N15: 2023 | O15: 0.082
B16: Gift Cards Promo % | C16: 0.2 | N16: 2024 | O16: 0.0831
N17: 2025 | O17: 0.0737
B18: Outputs
N20: Business Type | O20: Spread
B21: Est. Breakage Revenue | C21: =C10*C12 -> 7500 | N21: Large Corporation | O21: 0
B22: Gift Card Float Value | C22: =C10*(C13/12) -> 62500 | N22: Medium-Size Business | O22: 0.015
B23: Equivalent Annual Loan Interest | C23: =C10*C14 -> 4020 | N23: Small-Business | O23: 0.0275
B24: Total Annual Benefit | C24: =C21+C23 -> 11520 | N24: Startup | O24: 0.045
G30: GC Sales Volume | H30: Loan Cost Avoided | I30: Promotion Cost | J30: Net True Benefit | K30: Breakage Revenue
G31: 10000 | H31: =G31*$C$14 -> 804 | I31: =G31*$C$16 -> 2000 | J31: =H31+K31-I31 -> 304 | K31: =G31*$C$12 -> 1500
G32: 25000 | H32: =G32*$C$14 -> 2010 | I32: =G32*$C$16 -> 5000 | J32: =H32+K32-I32 -> 760 | K32: =G32*$C$12 -> 3750
G33: 50000 | H33: =G33*$C$14 -> 4020 | I33: =G33*$C$16 -> 10000 | J33: =H33+K33-I33 -> 1520 | K33: =G33*$C$12 -> 7500
G34: 100000 | H34: =G34*$C$14 -> 8040 | I34: =G34*$C$16 -> 20000 | J34: =H34+K34-I34 -> 3040 | K34: =G34*$C$12 -> 15000
G35: 250000 | H35: =G35*$C$14 -> 20100 | I35: =G35*$C$16 -> 50000 | J35: =H35+K35-I35 -> 7600 | K35: =G35*$C$12 -> 37500
G36: 500000 | H36: =G36*$C$14 -> 40200 | I36: =G36*$C$16 -> 100000 | J36: =H36+K36-I36 -> 15200 | K36: =G36*$C$12 -> 75000
G37: 1000000 | H37: =G37*$C$14 -> 80400 | I37: =G37*$C$16 -> 200000 | J37: =H37+K37-I37 -> 30400 | K37: =G37*$C$12 -> 150000
